setup.py
flowser/__init__.py
flowser/decisions.py
flowser/domain.py
flowser/events.py
flowser/exceptions.py
flowser/serializing.py
flowser/tasks.py
flowser/types.py
flowser.egg-info/PKG-INFO
flowser.egg-info/SOURCES.txt
flowser.egg-info/dependency_links.txt
flowser.egg-info/requires.txt
flowser.egg-info/top_level.txt