Metadata-Version: 1.0
Name: flowser
Version: 0.1.0
Summary: High-level interface for Amazon Simple Workflow
Home-page: https://github.com/pilt/flowser/
Author: Simon Pantzare
Author-email: simon+flowser@pewpewlabs.com
License: MIT
Platform: Posix; MacOS X; Windows
Classifier: Development Status :: 3 - Alpha
Classifier: Topic :: Internet
Classifier: Intended Audience :: Developers
Classifier: License :: OSI Approved :: MIT License
Classifier: Operating System :: OS Independent
Classifier: Programming Language :: Python :: 2
Classifier: Programming Language :: Python :: 2.7
